pyrepak/__init__.py
pyrepak/repak_bind.dll
pyrepak-0.0.7.dist-info/METADATA
pyrepak-0.0.7.dist-info/WHEEL
pyrepak-0.0.7.dist-info/top_level.txt
pyrepak-0.0.7.dist-info/RECORD
