Metadata-Version: 2.4
Name: pyrepak
Version: 0.0.7
Summary: PyRepak is a binding of repak libraries for working with Unreal Engine .pak files
Author-email: stas96111 <stas96111@gmail.com>
License: MIT License
Project-URL: Homepage, https://github.com/stas96111/pyrepak
Classifier: Programming Language :: Python :: 3
Classifier: Operating System :: OS Independent
Requires-Python: >=3.8
